inferless_cli/__init__.py
inferless_cli/__main__.py
inferless_cli/commands/__init__.py
inferless_cli/commands/deploy/constants.py
inferless_cli/commands/deploy/deploy_prompt.py
inferless_cli/commands/export/convertors.py
inferless_cli/commands/export/export_prompt.py
inferless_cli/commands/init/constants.py
inferless_cli/commands/init/helpers.py
inferless_cli/commands/init/init_prompt.py
inferless_cli/commands/integration/integration_prompt.py
inferless_cli/commands/integration/integration_sub_prompts.py
inferless_cli/commands/log/log_prompt.py
inferless_cli/commands/login/login_prompt.py
inferless_cli/commands/model/model_prompt.py
inferless_cli/commands/region/region_prompt.py
inferless_cli/commands/remote_run/remote_run_prompt.py
inferless_cli/commands/run/constants.py
inferless_cli/commands/run/helpers.py
inferless_cli/commands/run/run_prompt.py
inferless_cli/commands/runtime/runtime_prompt.py
inferless_cli/commands/scaffold/scaffold_prompt.py
inferless_cli/commands/secret/secret_prompt.py
inferless_cli/commands/token/token_prompt.py
inferless_cli/commands/volume/volume_prompt.py
inferless_cli/commands/workspace/workspace_prompt.py
inferless_cli/main.py
inferless_cli/utils/__init__.py
inferless_cli/utils/api.py
inferless_cli/utils/constants.py
inferless_cli/utils/credentials.py
inferless_cli/utils/exceptions.py
inferless_cli/utils/helpers.py
inferless_cli/utils/inferless_config_handler.py
inferless_cli/utils/services.py
inferless_cli/utils/validators.py
inferless_cli-2.0.21.dist-info/METADATA
inferless_cli-2.0.21.dist-info/WHEEL
inferless_cli-2.0.21.dist-info/entry_points.txt
inferless_cli-2.0.21.dist-info/RECORD
