Metadata-Version: 2.1
Name: inferless-cli
Version: 2.0.21
Summary: Inferless - Deploy Machine Learning Models in Minutes.
Author: Naveen
Author-email: naveen@inferless.com
Requires-Python: >=3.9,<4.0
Classifier: Programming Language :: Python :: 3
Classifier: Programming Language :: Python :: 3.9
Classifier: Programming Language :: Python :: 3.10
Classifier: Programming Language :: Python :: 3.11
Requires-Dist: astor (>=0.8.1,<0.9.0)
Requires-Dist: coverage (>=7.6.9,<8.0.0)
Requires-Dist: cryptography (>=42.0.5,<43.0.0)
Requires-Dist: docker (>=7.0.0,<8.0.0)
Requires-Dist: inferless (>=0.2.11,<0.3.0)
Requires-Dist: keyring (>=24.3.1,<25.0.0)
Requires-Dist: keyrings-alt (>=5.0.0,<6.0.0)
Requires-Dist: posthog (>=3.7.4,<4.0.0)
Requires-Dist: pydantic (>=2.10.6,<3.0.0)
Requires-Dist: pyjwt (>=2.8.0,<3.0.0)
Requires-Dist: pytest (>=8.3.4,<9.0.0)
Requires-Dist: python-dateutil (>=2.8.2,<3.0.0)
Requires-Dist: requests (>=2.31.0,<3.0.0)
Requires-Dist: ruamel-yaml (>=0.18.5,<0.19.0)
Requires-Dist: sentry-sdk (>=1.35.0,<2.0.0)
Requires-Dist: toml (>=0.10.2,<0.11.0)
Requires-Dist: typer[all] (>=0.9.0,<0.10.0)
